autogen_agentai/__init__.py
autogen_agentai/core.py
autogen_agentai-0.1.0.dist-info/LICENSE
autogen_agentai-0.1.0.dist-info/METADATA
autogen_agentai-0.1.0.dist-info/WHEEL
autogen_agentai-0.1.0.dist-info/RECORD
